lmo/__init__.py
lmo/_lm.py
lmo/_lm_co.py
lmo/_meta.py
lmo/_poly.py
lmo/_utils.py
lmo/constants.py
lmo/contrib/__init__.py
lmo/contrib/pandas.py
lmo/contrib/scipy_stats.py
lmo/diagnostic.py
lmo/distributions/__init__.py
lmo/distributions/_genlambda.py
lmo/distributions/_kumaraswamy.py
lmo/distributions/_lm.py
lmo/distributions/_nonparametric.py
lmo/distributions/_wakeby.py
lmo/inference/__init__.py
lmo/inference/_l_gmm.py
lmo/linalg.py
lmo/ostats.py
lmo/pwm_beta.py
lmo/py.typed
lmo/special.py
lmo/theoretical/__init__.py
lmo/theoretical/_f_to_f.py
lmo/theoretical/_f_to_h.py
lmo/theoretical/_f_to_lcm.py
lmo/theoretical/_f_to_lm.py
lmo/theoretical/_f_to_lm_cov.py
lmo/theoretical/_f_to_lm_eif.py
lmo/theoretical/_lm_to_f.py
lmo/theoretical/_utils.py
lmo/typing/__init__.py
lmo/typing/np.py
lmo/typing/scipy.py
lmo-0.14.2.dist-info/LICENSE
lmo-0.14.2.dist-info/METADATA
lmo-0.14.2.dist-info/WHEEL
lmo-0.14.2.dist-info/RECORD
