Metadata-Version: 2.1
Name: lmo
Version: 0.14.2
Summary: L-Moments for robust statistics & inference.
Home-page: https://jorenham.github.io/Lmo/
License: BSD-3-Clause
Author: Joren Hammudoglu
Author-email: jhammudoglu@gmail.com
Requires-Python: >=3.10.1,<4.0.0
Classifier: Development Status :: 4 - Beta
Classifier: Intended Audience :: Developers
Classifier: Intended Audience :: Education
Classifier: Intended Audience :: End Users/Desktop
Classifier: Intended Audience :: Financial and Insurance Industry
Classifier: Intended Audience :: Science/Research
Classifier: License :: OSI Approved :: BSD License
Classifier: Natural Language :: English
Classifier: Operating System :: OS Independent
Classifier: Programming Language :: Python :: 3
Classifier: Programming Language :: Python :: 3.11
Classifier: Programming Language :: Python :: 3.12
Classifier: Programming Language :: Python :: 3.10
Classifier: Programming Language :: Python :: 3.13
Classifier: Topic :: Office/Business :: Financial
Classifier: Topic :: Scientific/Engineering
Classifier: Topic :: Scientific/Engineering :: Hydrology
Classifier: Topic :: Scientific/Engineering :: Information Analysis
Classifier: Topic :: Scientific/Engineering :: Mathematics
Classifier: Topic :: Scientific/Engineering :: Physics
Classifier: Topic :: Utilities
Classifier: Typing :: Typed
Provides-Extra: pandas
Requires-Dist: numpy (>1.24)
Requires-Dist: optype[numpy] (>=0.6.1,<0.7.0)
Requires-Dist: pandas (>=1.5) ; extra == "pandas"
Requires-Dist: scipy (>=1.10.1,<2.0.0)
Requires-Dist: typing_extensions (>=4.8,<5.0) ; python_version < "3.13"
Project-URL: Bug Tracker, https://github.com/jorenham/Lmo/issues
Project-URL: Documentation, https://jorenham.github.io/Lmo/
Project-URL: Repository, https://github.com/jorenham/Lmo/
